cz_gitmoji/__init__.py
cz_gitmoji/conventional_gitmojis_info.txt
cz_gitmoji/main.py
gitmojify/__init__.py
gitmojify/mojify.py
shared/__init__.py
shared/gitmojis.py
shared/model.py
shared/spec.py
shared/utils.py
commitizen_gitmoji-0.1.1.dist-info/entry_points.txt
commitizen_gitmoji-0.1.1.dist-info/WHEEL
commitizen_gitmoji-0.1.1.dist-info/METADATA
commitizen_gitmoji-0.1.1.dist-info/RECORD
