Metadata-Version: 2.1
Name: commitizen-gitmoji
Version: 0.1.1
Summary: A commitizen plugin that combines gitmoji and conventional.
Home-page: https://github.com/ljnsn/cz-conventional-gitmoji
License: MIT
Author: ljnsn
Author-email: 82611987+ljnsn@users.noreply.github.com
Requires-Python: >=3.7,<4.0
Classifier: License :: OSI Approved :: MIT License
Classifier: Programming Language :: Python :: 3
Classifier: Programming Language :: Python :: 3.7
Classifier: Programming Language :: Python :: 3.8
Classifier: Programming Language :: Python :: 3.9
Classifier: Programming Language :: Python :: 3.10
Classifier: Programming Language :: Python :: 3.11
Requires-Dist: attrs (>=22.2.0,<23.0.0)
Requires-Dist: commitizen (>=2.38.0,<3.0.0)
Project-URL: Repository, https://github.com/ljnsn/cz-conventional-gitmoji
